forecastvh/__init__.py
forecastvh/weather.py
forecastvh-0.0.1b3.dist-info/LICENSE
forecastvh-0.0.1b3.dist-info/WHEEL
forecastvh-0.0.1b3.dist-info/METADATA
forecastvh-0.0.1b3.dist-info/RECORD
