Metadata-Version: 2.1
Name: forecastvh
Version: 0.0.1b3
Summary: Let's see the weather outside!
Home-page: https://github.com/MorningStar-png/weathervh-py
License: UNKNOWN
Author: Ilia Fedorovich
Author-email: workplaceilfed@gmail.com
Requires-Python: >=3.8
Classifier: License :: OSI Approved :: MIT License
Classifier: Programming Language :: Python :: 3
